AUTHORS.txt
LICENSE-BSD.txt
MANIFEST.in
NOTICE.txt
README.rst
setup.py
lucene_querybuilder.egg-info/PKG-INFO
lucene_querybuilder.egg-info/SOURCES.txt
lucene_querybuilder.egg-info/dependency_links.txt
lucene_querybuilder.egg-info/not-zip-safe
lucene_querybuilder.egg-info/top_level.txt
lucenequerybuilder/__init__.py
lucenequerybuilder/query.py
lucenequerybuilder/tests.py