Metadata-Version: 1.0
Name: lucene-querybuilder
Version: 0.2
Summary: A DSL to build Lucene text queries in Python.
Home-page: http://packages.python.org/lucene-querybuilder
Author: Matt Luongo
Author-email: mhluongo@gmail.com
License: UNKNOWN
Platform: posix
Classifier: Development Status :: 3 - Alpha
Classifier: Intended Audience :: Developers
Classifier: License :: OSI Approved :: BSD License
Classifier: Operating System :: POSIX
Classifier: Topic :: Text Processing :: Indexing
Classifier: Programming Language :: Python
